mfaultra/__init__.py
mfaultra/audit.py
mfaultra/auth.py
mfaultra/exceptions.py
mfaultra/ip_filter.py
mfaultra/limiter.py
mfaultra/mfa.py
mfaultra/password_policy.py
mfaultra/rbac.py
mfaultra/session.py
mfaultra/user.py
mfaultra-0.1.0.dist-info/licenses/LICENSE
mfaultra-0.1.0.dist-info/METADATA
mfaultra-0.1.0.dist-info/WHEEL
mfaultra-0.1.0.dist-info/top_level.txt
mfaultra-0.1.0.dist-info/RECORD
