Metadata-Version: 2.4
Name: MFAultra
Version: 0.1.0
Summary: 一个功能强大的身份验证模块，支持多因素认证和RBAC权限系统
Home-page: https://www.douyin.com/user/MS4wLjABAAAACQczOtUtm27WBmLg8dcGpgTrWXR6LjKp2lyJJS3XwnM?from_tab_name=main
Author: LitDDD
Author-email: cz_a340-600@qq.com
Classifier: Programming Language :: Python :: 3
Classifier: License :: OSI Approved :: MIT License
Classifier: Operating System :: OS Independent
Requires-Python: >=3.11
License-File: LICENSE
Requires-Dist: pyotp>=2.8.0
Requires-Dist: bcrypt>=4.0.1
Dynamic: author
Dynamic: author-email
Dynamic: classifier
Dynamic: description
Dynamic: description-content-type
Dynamic: home-page
Dynamic: license-file
Dynamic: requires-dist
Dynamic: requires-python
Dynamic: summary
